LICENSE.txt
MANIFEST.in
README.rst
setup.cfg
setup.py
simctl/__init__.py
simctl/device.py
simctl/device_type.py
simctl/executor.py
simctl/list_device.py
simctl/runtime.py
simctl/timeout.py
simctl.egg-info/PKG-INFO
simctl.egg-info/SOURCES.txt
simctl.egg-info/dependency_links.txt
simctl.egg-info/requires.txt
simctl.egg-info/top_level.txt