Metadata-Version: 1.1
Name: simctl
Version: 0.0.2
Summary: A Python project for Apple's simctl
Home-page: https://github.com/oliverhu/simctl.git
Author: The Python Packaging Authority
Author-email: pypa-dev@googlegroups.com
License: MIT
Keywords: Apple dev tools
Platform: UNKNOWN
Classifier: Development Status :: 3 - Alpha
Classifier: Intended Audience :: Developers
Classifier: Topic :: Software Development :: Build Tools
Classifier: License :: OSI Approved :: MIT License
Classifier: Programming Language :: Python :: 2
Classifier: Programming Language :: Python :: 2.6
Classifier: Programming Language :: Python :: 2.7
Classifier: Programming Language :: Python :: 3
Classifier: Programming Language :: Python :: 3.3
Classifier: Programming Language :: Python :: 3.4
Classifier: Programming Language :: Python :: 3.5
